quantalogic_codeact/__init__.py
quantalogic_codeact/__main__.py
quantalogic_codeact/cli.py
quantalogic_codeact/cli_commands/__init__.py
quantalogic_codeact/cli_commands/config.py
quantalogic_codeact/cli_commands/config_constants.py
quantalogic_codeact/cli_commands/config_functions.py
quantalogic_codeact/cli_commands/config_load.py
quantalogic_codeact/cli_commands/config_manager.py
quantalogic_codeact/cli_commands/config_utils.py
quantalogic_codeact/cli_commands/create_toolbox.py
quantalogic_codeact/cli_commands/install_toolbox.py
quantalogic_codeact/cli_commands/list_executor.py
quantalogic_codeact/cli_commands/list_models.py
quantalogic_codeact/cli_commands/list_reasoners.py
quantalogic_codeact/cli_commands/list_toolboxes.py
quantalogic_codeact/cli_commands/task.py
quantalogic_codeact/cli_commands/tool_info.py
quantalogic_codeact/cli_commands/toolbox.py
quantalogic_codeact/cli_commands/uninstall_toolbox.py
quantalogic_codeact/cli_commands/version.py
quantalogic_codeact/codeact/__init__.py
quantalogic_codeact/codeact/agent.py
quantalogic_codeact/codeact/agent_config.py
quantalogic_codeact/codeact/codeact_agent.py
quantalogic_codeact/codeact/completion_evaluator.py
quantalogic_codeact/codeact/constants.py
quantalogic_codeact/codeact/conversation_manager.py
quantalogic_codeact/codeact/events.py
quantalogic_codeact/codeact/executor.py
quantalogic_codeact/codeact/llm_util.py
quantalogic_codeact/codeact/message.py
quantalogic_codeact/codeact/personality_config.py
quantalogic_codeact/codeact/plugin_manager.py
quantalogic_codeact/codeact/prompts/action_program.j2
quantalogic_codeact/codeact/prompts/is_task_complete.j2
quantalogic_codeact/codeact/prompts/response_format.j2
quantalogic_codeact/codeact/prompts/step.j2
quantalogic_codeact/codeact/prompts/system_prompt.j2
quantalogic_codeact/codeact/reasoner.py
quantalogic_codeact/codeact/templates.py
quantalogic_codeact/codeact/tools/__init__.py
quantalogic_codeact/codeact/tools/agent_tool.py
quantalogic_codeact-0.100.0.dist-info/METADATA
quantalogic_codeact-0.100.0.dist-info/WHEEL
quantalogic_codeact-0.100.0.dist-info/entry_points.txt
quantalogic_codeact-0.100.0.dist-info/RECORD
