Metadata-Version: 2.3
Name: quantalogic-codeact
Version: 0.100.0
Summary: CodeAct Agent.
License: Apache-2.0
Author: Raphael Mansuy
Author-email: raphae.mansuy@quantalogic.app
Requires-Python: >=3.9,<4.0
Classifier: License :: OSI Approved :: Apache Software License
Classifier: Programming Language :: Python :: 3
Classifier: Programming Language :: Python :: 3.9
Classifier: Programming Language :: Python :: 3.10
Classifier: Programming Language :: Python :: 3.11
Classifier: Programming Language :: Python :: 3.12
Classifier: Programming Language :: Python :: 3.13
Requires-Dist: docstring-parser (>=0.15,<1.0)
Requires-Dist: jinja2 (>=3.1.6,<4.0.0)
Requires-Dist: litellm (>=1.66.2,<2.0.0)
Requires-Dist: loguru (>=0.7.3,<0.8.0)
Requires-Dist: lxml (>=5.3.2,<6.0.0)
Requires-Dist: pydantic (>=1.10,<3.0)
Requires-Dist: quantalogic-pythonbox (>=0.9.12,<0.10.0)
Requires-Dist: quantalogic-toolbox (>=0.11.0)
Requires-Dist: rich (>=14.0.0,<15.0.0)
Requires-Dist: typer (>=0.15.2,<0.16.0)
